{"summaries":[{"symbol":{"__symbol":0,"members":[]},"metadata":{"__symbolic":"interface"}},{"symbol":{"__symbol":1,"members":[]},"metadata":{"__symbolic":"class","extends":{"__symbol":2,"members":[]},"members":{"getPreferredLanguage":[{"__symbolic":"method","decorators":[{"__symbolic":"call","expression":{"__symbol":3,"members":[]}}]}],"getLocaleName":[{"__symbolic":"method","decorators":[{"__symbolic":"call","expression":{"__symbol":3,"members":[]}}]}],"dateToString":[{"__symbolic":"method","decorators":[{"__symbolic":"call","expression":{"__symbol":3,"members":[]},"arguments":[{"successIndex":1,"errorIndex":2}]}]}],"stringToDate":[{"__symbolic":"method","decorators":[{"__symbolic":"call","expression":{"__symbol":3,"members":[]},"arguments":[{"successIndex":1,"errorIndex":2}]}]}],"getDatePattern":[{"__symbolic":"method","decorators":[{"__symbolic":"call","expression":{"__symbol":3,"members":[]},"arguments":[{"callbackOrder":"reverse"}]}]}],"getDateNames":[{"__symbolic":"method","decorators":[{"__symbolic":"call","expression":{"__symbol":3,"members":[]},"arguments":[{"callbackOrder":"reverse"}]}]}],"isDayLightSavingsTime":[{"__symbolic":"method","decorators":[{"__symbolic":"call","expression":{"__symbol":3,"members":[]}}]}],"getFirstDayOfWeek":[{"__symbolic":"method","decorators":[{"__symbolic":"call","expression":{"__symbol":3,"members":[]}}]}],"numberToString":[{"__symbolic":"method","decorators":[{"__symbolic":"call","expression":{"__symbol":3,"members":[]},"arguments":[{"successIndex":1,"errorIndex":2}]}]}],"stringToNumber":[{"__symbolic":"method","decorators":[{"__symbolic":"call","expression":{"__symbol":3,"members":[]},"arguments":[{"successIndex":1,"errorIndex":2}]}]}],"getNumberPattern":[{"__symbolic":"method","decorators":[{"__symbolic":"call","expression":{"__symbol":3,"members":[]},"arguments":[{"callbackOrder":"reverse"}]}]}],"getCurrencyPattern":[{"__symbolic":"method","decorators":[{"__symbolic":"call","expression":{"__symbol":3,"members":[]}}]}]}},"type":{"summaryKind":3,"type":{"reference":{"__symbol":1,"members":[]},"diDeps":[],"lifecycleHooks":[]}}}],"symbols":[{"__symbol":0,"name":"GlobalizationOptions","filePath":"/Users/chandan/Work/Tke_Mobility/Tke_Mobility_Dev/ionic-native/src/@ionic-native/plugins/globalization/index.d.ts"},{"__symbol":1,"name":"Globalization","filePath":"/Users/chandan/Work/Tke_Mobility/Tke_Mobility_Dev/ionic-native/src/@ionic-native/plugins/globalization/index.d.ts"},{"__symbol":2,"name":"IonicNativePlugin","filePath":"/Users/chandan/Work/Tke_Mobility/Tke_Mobility_Dev/ionic-native/dist/@ionic-native/core/index.d.ts"},{"__symbol":3,"name":"Cordova","filePath":"/Users/chandan/Work/Tke_Mobility/Tke_Mobility_Dev/ionic-native/dist/@ionic-native/core/index.d.ts"}]}