{"summaries":[{"symbol":{"__symbol":0,"members":[]},"metadata":{"__symbolic":"class","extends":{"__symbol":1,"members":[]},"members":{"connect":[{"__symbolic":"method","decorators":[{"__symbolic":"call","expression":{"__symbol":2,"members":[]},"arguments":[{"platforms":["Android","iOS","Windows Phone"],"observable":true,"clearFunction":"disconnect"}]}]}],"connectInsecure":[{"__symbolic":"method","decorators":[{"__symbolic":"call","expression":{"__symbol":2,"members":[]},"arguments":[{"platforms":["Android"],"observable":true,"clearFunction":"disconnect"}]}]}],"disconnect":[{"__symbolic":"method","decorators":[{"__symbolic":"call","expression":{"__symbol":2,"members":[]}}]}],"write":[{"__symbolic":"method","decorators":[{"__symbolic":"call","expression":{"__symbol":2,"members":[]},"arguments":[{"platforms":["Android","iOS","Windows Phone"]}]}]}],"available":[{"__symbolic":"method","decorators":[{"__symbolic":"call","expression":{"__symbol":2,"members":[]},"arguments":[{"platforms":["Android","iOS","Windows Phone"]}]}]}],"read":[{"__symbolic":"method","decorators":[{"__symbolic":"call","expression":{"__symbol":2,"members":[]},"arguments":[{"platforms":["Android","iOS","Windows Phone"]}]}]}],"readUntil":[{"__symbolic":"method","decorators":[{"__symbolic":"call","expression":{"__symbol":2,"members":[]},"arguments":[{"platforms":["Android","iOS","Windows Phone"]}]}]}],"subscribe":[{"__symbolic":"method","decorators":[{"__symbolic":"call","expression":{"__symbol":2,"members":[]},"arguments":[{"platforms":["Android","iOS","Windows Phone"],"observable":true,"clearFunction":"unsubscribe"}]}]}],"subscribeRawData":[{"__symbolic":"method","decorators":[{"__symbolic":"call","expression":{"__symbol":2,"members":[]},"arguments":[{"platforms":["Android","iOS","Windows Phone"],"observable":true,"clearFunction":"unsubscribeRawData"}]}]}],"clear":[{"__symbolic":"method","decorators":[{"__symbolic":"call","expression":{"__symbol":2,"members":[]},"arguments":[{"platforms":["Android","iOS","Windows Phone"]}]}]}],"list":[{"__symbolic":"method","decorators":[{"__symbolic":"call","expression":{"__symbol":2,"members":[]},"arguments":[{"platforms":["Android","iOS","Windows Phone"]}]}]}],"isEnabled":[{"__symbolic":"method","decorators":[{"__symbolic":"call","expression":{"__symbol":2,"members":[]},"arguments":[{"platforms":["Android","iOS","Windows Phone"]}]}]}],"isConnected":[{"__symbolic":"method","decorators":[{"__symbolic":"call","expression":{"__symbol":2,"members":[]},"arguments":[{"platforms":["Android","iOS","Windows Phone"]}]}]}],"readRSSI":[{"__symbolic":"method","decorators":[{"__symbolic":"call","expression":{"__symbol":2,"members":[]},"arguments":[{"platforms":["Android","iOS","Windows Phone"]}]}]}],"showBluetoothSettings":[{"__symbolic":"method","decorators":[{"__symbolic":"call","expression":{"__symbol":2,"members":[]},"arguments":[{"platforms":["Android","iOS","Windows Phone"]}]}]}],"enable":[{"__symbolic":"method","decorators":[{"__symbolic":"call","expression":{"__symbol":2,"members":[]},"arguments":[{"platforms":["Android","iOS","Windows Phone"]}]}]}],"discoverUnpaired":[{"__symbolic":"method","decorators":[{"__symbolic":"call","expression":{"__symbol":2,"members":[]},"arguments":[{"platforms":["Android","iOS","Windows Phone"]}]}]}],"setDeviceDiscoveredListener":[{"__symbolic":"method","decorators":[{"__symbolic":"call","expression":{"__symbol":2,"members":[]},"arguments":[{"platforms":["Android","iOS","Windows Phone"],"observable":true,"clearFunction":"clearDeviceDiscoveredListener"}]}]}],"setName":[{"__symbolic":"method","decorators":[{"__symbolic":"call","expression":{"__symbol":2,"members":[]},"arguments":[{"platforms":["Android"],"sync":true}]}]}],"setDiscoverable":[{"__symbolic":"method","decorators":[{"__symbolic":"call","expression":{"__symbol":2,"members":[]},"arguments":[{"platforms":["Android"],"sync":true}]}]}]}},"type":{"summaryKind":3,"type":{"reference":{"__symbol":0,"members":[]},"diDeps":[],"lifecycleHooks":[]}}}],"symbols":[{"__symbol":0,"name":"BluetoothSerial","filePath":"/Users/chandan/Work/Tke_Mobility/Tke_Mobility_Dev/ionic-native/src/@ionic-native/plugins/bluetooth-serial/index.d.ts"},{"__symbol":1,"name":"IonicNativePlugin","filePath":"/Users/chandan/Work/Tke_Mobility/Tke_Mobility_Dev/ionic-native/dist/@ionic-native/core/index.d.ts"},{"__symbol":2,"name":"Cordova","filePath":"/Users/chandan/Work/Tke_Mobility/Tke_Mobility_Dev/ionic-native/dist/@ionic-native/core/index.d.ts"}]}